setup.py
xkcd_wallpaper.egg-info/PKG-INFO
xkcd_wallpaper.egg-info/SOURCES.txt
xkcd_wallpaper.egg-info/dependency_links.txt
xkcd_wallpaper.egg-info/entry_points.txt
xkcd_wallpaper.egg-info/requires.txt
xkcd_wallpaper.egg-info/top_level.txt
xkcdwall/__init__.py
xkcdwall/cmd.py