Metadata-Version: 1.0
Name: xkcd-wallpaper
Version: 1.0
Summary: Script that sets the latest XKCD comic as your wallpaper
Home-page: UNKNOWN
Author: saru95
Author-email: UNKNOWN
License: MIT
Platform: UNKNOWN
